tagged_union/__init__.py
tests/__init__.py
tests/test_tagged_union.py
tagged_union-0.0.1.dist-info/LICENSE.txt
tagged_union-0.0.1.dist-info/METADATA
tagged_union-0.0.1.dist-info/WHEEL
tagged_union-0.0.1.dist-info/top_level.txt
tagged_union-0.0.1.dist-info/RECORD
